{
  "generated_at": "2026-07-01T12:16:53+08:00",
  "competition_name": "2026 世界杯",
  "matches": [
    {
      "match_id": "M081",
      "kickoff_at": "2026-07-02T08:00:00+08:00",
      "stage": "1/16决赛",
      "team_a": "德国",
      "team_b": "南非",
      "team_a_id": "ger",
      "team_b_id": "rsa",
      "venue": "旧金山Levis体育场",
      "has_predict": false,
      "bets": {
        "H": [],
        "D": [],
        "A": []
      },
      "comment": {},
      "score": null,
      "predictions": [],
      "odds": null,
      "bets_detail": [],
      "status": "",
      "prediction_status": "已预测"
    }
  ],
  "models": []
}